PipPackageCustomInstaller.py
__init__.py
PipPackageCustomInstaller-1.0.0.dist-info/LICENSE
PipPackageCustomInstaller-1.0.0.dist-info/METADATA
PipPackageCustomInstaller-1.0.0.dist-info/WHEEL
PipPackageCustomInstaller-1.0.0.dist-info/top_level.txt
PipPackageCustomInstaller-1.0.0.dist-info/RECORD
