Metadata-Version: 2.1
Name: PipPackageCustomInstaller
Version: 1.0.0
Summary: Descripción del paquete
Home-page: https://github.com/JorgeCardona/PipPackageInstaller
Author: Jorge Cardona
Classifier: Programming Language :: Python :: 3
Classifier: License :: OSI Approved :: MIT License
Classifier: Operating System :: OS Independent
Requires-Python: >=3.6
License-File: LICENSE
